ncbPy/__init__.py
ncbPy/ncbi.py
ncbPy-0.1.0.dist-info/METADATA
ncbPy-0.1.0.dist-info/RECORD
ncbPy-0.1.0.dist-info/WHEEL
ncbPy-0.1.0.dist-info/top_level.txt
